{"basename":"apache2","fileperms":"0755","filetype":"dir","is_readable":true,"is_writeable":false,"is_link":false,"is_dir":true,"mime":"directory","mtime":1722404912,"path":"etc/apache2","dirsize":null,"files_count":null,"images_count":null,"preview":null,"files":{"conf-available":{"basename":"conf-available","fileperms":"0755","filetype":"dir","filesize":false,"is_readable":true,"is_writeable":false,"is_link":false,"is_dir":true,"mtime":1756783229,"path":"etc/apache2/conf-available","mime":"directory"},"mods-available":{"basename":"mods-available","fileperms":"0755","filetype":"dir","filesize":false,"is_readable":true,"is_writeable":false,"is_link":false,"is_dir":true,"mtime":1722404912,"path":"etc/apache2/mods-available","mime":"directory"}}}